example/__init__.py
example/simple.py
scidownl/__init__.py
scidownl/config.py
scidownl/exception.py
scidownl/log.py
scidownl/api/__init__.py
scidownl/api/cli.py
scidownl/api/scihub.py
scidownl/config/global.ini
scidownl/core/__init__.py
scidownl/core/base.py
scidownl/core/chooser.py
scidownl/core/content.py
scidownl/core/crawler.py
scidownl/core/downloader.py
scidownl/core/extractor.py
scidownl/core/information.py
scidownl/core/source.py
scidownl/core/task.py
scidownl/core/updater.py
scidownl/db/__init__.py
scidownl/db/entities.py
scidownl/db/service.py
scidownl-1.0.2.dist-info/LICENSE
scidownl-1.0.2.dist-info/METADATA
scidownl-1.0.2.dist-info/WHEEL
scidownl-1.0.2.dist-info/entry_points.txt
scidownl-1.0.2.dist-info/top_level.txt
scidownl-1.0.2.dist-info/RECORD
