Metadata-Version: 2.1
Name: scidownl
Version: 1.0.2
Summary: Download pdfs from Scihub.
Home-page: https://github.com/Tishacy/SciDownl
Author: Tishacy
Author-email: Tishacy@gmail.com
License: UNKNOWN
Platform: UNKNOWN
Classifier: Programming Language :: Python :: 3
Classifier: Programming Language :: Python :: 3.5
Classifier: Programming Language :: Python :: 3.6
Classifier: Programming Language :: Python :: 3.7
Classifier: License :: OSI Approved :: MIT License
Classifier: Operating System :: OS Independent
License-File: LICENSE
